thai_drg_grouper/__init__.py
thai_drg_grouper/api.py
thai_drg_grouper/cli.py
thai_drg_grouper/grouper.py
thai_drg_grouper/manager.py
thai_drg_grouper/types.py
thai_drg_grouper-2.2.0.dist-info/METADATA
thai_drg_grouper-2.2.0.dist-info/WHEEL
thai_drg_grouper-2.2.0.dist-info/entry_points.txt
thai_drg_grouper-2.2.0.dist-info/licenses/LICENSE
thai_drg_grouper-2.2.0.dist-info/RECORD
